pybind11_rdp/__init__.py
pybind11_rdp/__init__.pyi
pybind11_rdp/_core.cp313-win_amd64.pyd
pybind11_rdp-0.1.5.dist-info/METADATA
pybind11_rdp-0.1.5.dist-info/WHEEL
pybind11_rdp-0.1.5.dist-info/licenses/LICENSE
pybind11_rdp-0.1.5.dist-info/RECORD
