Metadata-Version: 2.1
Name: pybind11-rdp
Version: 0.1.5
Summary: C++/pybind11/NumPy implementation of the Ramer-Douglas-Peucker algorithm (Ramer 1972; Douglas and Peucker 1973) for 2D and 3D data.
Author-Email: tzx <dvorak4tzx@gmail.com>
Classifier: Development Status :: 4 - Beta
Classifier: License :: OSI Approved :: MIT License
Classifier: Programming Language :: Python :: 3 :: Only
Classifier: Programming Language :: Python :: 3.7
Classifier: Programming Language :: Python :: 3.8
Classifier: Programming Language :: Python :: 3.9
Classifier: Programming Language :: Python :: 3.10
Classifier: Programming Language :: Python :: 3.11
Classifier: Programming Language :: Python :: 3.12
Classifier: Programming Language :: Python :: 3.13
Project-URL: Homepage, https://github.com/cubao/pybind11-rdp
Project-URL: Repository, https://github.com/cubao/pybind11-rdp.git
Requires-Python: >=3.7
Requires-Dist: numpy
Requires-Dist: pytest; extra == "test"
Provides-Extra: test
